cat_data_tools/__init__.py
cat_data_tools/adapters.py
cat_data_tools/captures_list.py
cat_data_tools/cli.py
cat_data_tools/default_traps_list
cat_data_tools/filter_data_between_years.py
cat_data_tools/filter_data_by_month.py
cat_data_tools/trap_status_list.py
cat_data_tools/update_status_traps.py
cat_data_tools-0.10.0.dist-info/entry_points.txt
cat_data_tools-0.10.0.dist-info/licenses/LICENSE
cat_data_tools-0.10.0.dist-info/WHEEL
cat_data_tools-0.10.0.dist-info/METADATA
cat_data_tools-0.10.0.dist-info/RECORD
