Metadata-Version: 2.4
Name: cat_data_tools
Version: 0.10.0
Summary: A template Python module
Home-page: https://github.com/IslasGECI/cat_data_tools
Author: Ciencia de Datos • GECI
Author-email: ciencia.datos@islas.org.mx
Requires-Python: >=3.9
Classifier: License :: OSI Approved :: GNU General Public License v3 or later (GPLv3+)
License-File: LICENSE
Requires-Dist: numpy
Requires-Dist: pandas
Requires-Dist: typer[all]
